{
  "EndPoints": [
  {
    "Protocol": "https",
    "Host": "api.sitetest3.robloxlabs.com",
    "RelyingParty": "https://api.sitetest3.robloxlabs.com/",
    "TokenType": "JWT",
    "HostType": "fqdn"
  },
  {
    "Protocol": "https",
    "Host": "api.sitetest2.robloxlabs.com",
    "RelyingParty": "https://api.sitetest2.robloxlabs.com/",
    "TokenType": "JWT",
    "HostType": "fqdn"
  },
  {
    "Protocol": "https",
    "Host": "api.sitetest1.robloxlabs.com",
    "RelyingParty": "https://api.sitetest1.robloxlabs.com/",
    "TokenType": "JWT",
    "HostType": "fqdn"
  },
  {
    "Protocol": "https",
    "Host": "api.gametest5.robloxlabs.com",
    "RelyingParty": "https://api.gametest5.robloxlabs.com/",
    "TokenType": "JWT",
    "HostType": "fqdn"
  },
  {
    "Protocol": "https",
    "Host": "api.gametest4.robloxlabs.com",
    "RelyingParty": "https://api.gametest4.robloxlabs.com/",
    "TokenType": "JWT",
    "HostType": "fqdn"
  },
  {
    "Protocol": "https",
    "Host": "api.gametest3.robloxlabs.com",
    "RelyingParty": "https://api.gametest3.robloxlabs.com/",
    "TokenType": "JWT",
    "HostType": "fqdn"
  },
  {
    "Protocol": "https",
    "Host": "api.gametest2.robloxlabs.com",
    "RelyingParty": "https://api.gametest2.robloxlabs.com/",
    "TokenType": "JWT",
    "HostType": "fqdn"
  },
  {
    "Protocol": "https",
    "Host": "api.gametest1.robloxlabs.com",
    "RelyingParty": "https://api.gametest1.robloxlabs.com/",
    "TokenType": "JWT",
    "HostType": "fqdn"
  },
  {
    "Protocol": "https",
    "Host": "api.roblox.com",
    "RelyingParty": "https://api.roblox.com/",
    "TokenType": "JWT",
    "HostType": "fqdn"
  },
  {
    "Protocol": "https",
    "Host": "*",
    "RelyingParty": "http://xboxlive.com",
    "TokenType": "JWT",
    "HostType": "ip"
  },
  {
    "Protocol": "https",
    "Host": "*",
    "HostType": "wildcard"
  },
  {
    "Protocol": "http",
    "Host": "*",
    "HostType": "wildcard"
  }]
}